auto_docString/__init__.py
auto_docString/core.py
AutodocStringFormater-0.1.dist-info/METADATA
AutodocStringFormater-0.1.dist-info/WHEEL
AutodocStringFormater-0.1.dist-info/entry_points.txt
AutodocStringFormater-0.1.dist-info/top_level.txt
AutodocStringFormater-0.1.dist-info/RECORD
